sprinter/__init__.py
sprinter/environment.py
sprinter/exceptions.py
sprinter/install.py
sprinter/testtools.py
sprinter/core/__init__.py
sprinter/core/core.py
sprinter/core/directory.py
sprinter/core/featureconfig.py
sprinter/core/featuredict.py
sprinter/core/globals.py
sprinter/core/injections.py
sprinter/core/inputs.py
sprinter/core/manifest.py
sprinter/core/messages.py
sprinter/core/templates.py
sprinter/core/tests/__init__.py
sprinter/core/tests/test_directory.py
sprinter/core/tests/test_featureconfig.py
sprinter/core/tests/test_featuredict.py
sprinter/core/tests/test_globals.py
sprinter/core/tests/test_injections.py
sprinter/core/tests/test_inputs.py
sprinter/core/tests/test_manifest.py
sprinter/external/__init__.py
sprinter/external/brew.py
sprinter/external/pippuppet.py
sprinter/formula/__init__.py
sprinter/formula/base.py
sprinter/formula/command.py
sprinter/formula/eggscript.py
sprinter/formula/env.py
sprinter/formula/git.py
sprinter/formula/package.py
sprinter/formula/perforce.py
sprinter/formula/pex_package.py
sprinter/formula/ssh.py
sprinter/formula/template.py
sprinter/formula/unpack.py
sprinter/formula/tests/__init__.py
sprinter/formula/tests/test_base.py
sprinter/formula/tests/test_command.py
sprinter/formula/tests/test_eggscript.py
sprinter/formula/tests/test_env.py
sprinter/formula/tests/test_git.py
sprinter/formula/tests/test_package.py
sprinter/formula/tests/test_perforce.py
sprinter/formula/tests/test_ssh.py
sprinter/formula/tests/test_template.py
sprinter/formula/tests/test_unpack.py
sprinter/lib/__init__.py
sprinter/lib/command.py
sprinter/lib/compatability.py
sprinter/lib/dependencytree.py
sprinter/lib/extract.py
sprinter/lib/module.py
sprinter/lib/request.py
sprinter/lib/structures.py
sprinter/lib/system.py
sprinter/lib/tests/__init__.py
sprinter/lib/tests/test_command.py
sprinter/lib/tests/test_dependencytree.py
sprinter/lib/tests/test_lib.py
sprinter-1.4.2.dist-info/DESCRIPTION.rst
sprinter-1.4.2.dist-info/METADATA
sprinter-1.4.2.dist-info/RECORD
sprinter-1.4.2.dist-info/WHEEL
sprinter-1.4.2.dist-info/entry_points.txt
sprinter-1.4.2.dist-info/metadata.json
sprinter-1.4.2.dist-info/top_level.txt
