Metadata-Version: 2.0
Name: sprinter
Version: 1.4.2
Summary: a utility library to help environment bootstrapping scripts
Home-page: http://toumorokoshi.github.io/sprinter
Author: Yusuke Tsutsumi
Author-email: yusuke@yusuketsutsumi.com
License: UNKNOWN
Platform: UNKNOWN
Classifier: Development Status :: 5 - Production/Stable
Classifier: Operating System :: MacOS
Classifier: Operating System :: POSIX :: Linux
Classifier: Topic :: System :: Software Distribution
Classifier: License :: OSI Approved :: MIT License
Classifier: Programming Language :: Python
Classifier: Programming Language :: Python :: 2.6
Classifier: Programming Language :: Python :: 2.7
Classifier: Programming Language :: Python :: 3
Classifier: Programming Language :: Python :: 3.3
Requires-Dist: clint (>=0.3.3)
Requires-Dist: docopt (>=0.6.1)
Requires-Dist: pex (==1.1.0)
Requires-Dist: pip (==7.1.0)
Requires-Dist: requests (>=2.3.0)
Requires-Dist: six (>=1.4.1)
Requires-Dist: virtualenv (>=1.11.6)
